[
    {
        "time": 0,
        "text": "",
        "interlude": true
    },
    {
        "time": 24307,
        "text": "何かが足りない いつからだろう",
        "cn": "有什么总是无法满足 是从何时开始"
    },
    {
        "time": 26554,
        "text": "時に流され 考えてんだ",
        "cn": "为时流所驱 不断思考着"
    },
    {
        "time": 29009,
        "text": "すぐそこに咲く 微かな音を",
        "cn": "就在身旁绽放着 那细微的声音"
    },
    {
        "time": 31413,
        "text": "隠して征った 月が照らす",
        "cn": "将其隐藏起来 月光悄然洒下"
    },
    {
        "time": 33633,
        "text": "",
        "interlude": true
    },
    {
        "time": 33947,
        "text": "夜に包まれ 眠くもなくて",
        "cn": "躺在夜的怀抱里 睡意却不肯露面"
    },
    {
        "time": 36298,
        "text": "宇宙みたいな 終電日記",
        "cn": "仿佛宇宙一般的 末班车日记"
    },
    {
        "time": 38649,
        "text": "あの日の僕を 忘れるように",
        "cn": "像是将那一天的我忘却一般"
    },
    {
        "time": 41000,
        "text": "守れるように 息をするんだ",
        "cn": "又像是守护着一般 呼吸着呢"
    },
    {
        "time": 43586,
        "text": "",
        "interlude": true
    },
    {
        "time": 43769,
        "text": "辛いなんて 水平線融けてくままに",
        "cn": "难过的回忆 任其融化在水平线上"
    },
    {
        "time": 47661,
        "text": "今日はどうか 許してくれやしないか",
        "cn": "唯有今日 能否请你原谅我呢"
    },
    {
        "time": 52624,
        "text": "",
        "interlude": true
    },
    {
        "time": 53120,
        "text": "Sorrow Day 何もない人生を笑え",
        "cn": "Sorrow Day 嘲笑那空无一物的人生吧"
    },
    {
        "time": 55811,
        "text": "ゆらりゆら揺れる風に乗って",
        "cn": "乘上荡漾着飘过的风"
    },
    {
        "time": 58031,
        "text": "微睡む世界にじゃあね",
        "cn": "向浅睡朦胧的世界告别"
    },
    {
        "time": 59938,
        "text": "季節に漂うだけ",
        "cn": "仅仅摇荡在季节之中"
    },
    {
        "time": 61924,
        "text": "",
        "interlude": true
    },
    {
        "time": 62655,
        "text": "薄明かり星空零れたんだ",
        "cn": "明灭点点的星空挥洒出来"
    },
    {
        "time": 65372,
        "text": "今を肯定してほしいって",
        "cn": "说是想要肯定这个当下"
    },
    {
        "time": 67618,
        "text": "ありふれた感情 笑いあってさ",
        "cn": "在抑制不住的感情中相视而笑"
    },
    {
        "time": 70518,
        "text": "波立つ ミッドナイト",
        "cn": "风抚浪起 midnight"
    },
    {
        "time": 72347,
        "text": "",
        "interlude": true
    },
    {
        "time": 93375,
        "text": "気がつけば 雨が降ってた",
        "cn": "回过神来 雨点不断落下"
    },
    {
        "time": 95752,
        "text": "様な心地の 憂いの後に",
        "cn": "那样的心境 是忧愁的余韵"
    },
    {
        "time": 97973,
        "text": "また疑問符を 聴かないように",
        "cn": "再次像是 没有听见疑问号一般"
    },
    {
        "time": 100324,
        "text": "目をつむってさ 漂ってんだ",
        "cn": "拉上眼帘 任此身浮沉"
    },
    {
        "time": 102884,
        "text": "",
        "interlude": true
    },
    {
        "time": 103171,
        "text": "こうやって周りと歩いていたら",
        "cn": "就这样与周围一样行走的话"
    },
    {
        "time": 107220,
        "text": "人並みになったことになるのかな？",
        "cn": "就相当于成为普通人了吗？"
    },
    {
        "time": 112053,
        "text": "",
        "interlude": true
    },
    {
        "time": 112575,
        "text": "Cry Day 今日もそっと零れたもの",
        "cn": "Cry Day 今日也悄然零落了什么"
    },
    {
        "time": 115292,
        "text": "精一杯の歩幅だったの",
        "cn": "尽管是用尽全力的步伐"
    },
    {
        "time": 117747,
        "text": "たちまち夕に染まって",
        "cn": "夕阳于一瞬染上世界"
    },
    {
        "time": 119498,
        "text": "視界が滲んでゆく",
        "cn": "视野也逐渐朦胧起来"
    },
    {
        "time": 121457,
        "text": "大人になれば強くなれると信じていた",
        "cn": "一直坚信着成为大人就能变得坚强"
    },
    {
        "time": 124539,
        "text": "気が付けばガラスみたいな言葉",
        "cn": "回过神来却是那些不堪一击的话语"
    },
    {
        "time": 126942,
        "text": "傷を作りたがりな今をさ",
        "cn": "仿佛将渴望受伤的如今"
    },
    {
        "time": 129920,
        "text": "抱きしめるように",
        "cn": "拥入怀中一般"
    },
    {
        "time": 131618,
        "text": "",
        "interlude": true
    },
    {
        "time": 150557,
        "text": "Sorrow Day 何も無い人生を笑え",
        "cn": "Sorrow Day 嘲笑那空无一物的人生吧"
    },
    {
        "time": 153248,
        "text": "ゆらりゆら揺れる風に乗って",
        "cn": "乘上荡漾着飘过的风"
    },
    {
        "time": 155599,
        "text": "微睡む世界にじゃあね",
        "cn": "向浅睡朦胧的世界告别"
    },
    {
        "time": 157558,
        "text": "季節に漂うだけ",
        "cn": "仅仅摇荡在季节之中"
    },
    {
        "time": 159517,
        "text": "",
        "interlude": true
    },
    {
        "time": 159648,
        "text": "意味もなくそうやって歌ってたくて",
        "cn": "并无什么意义也想要如此歌唱"
    },
    {
        "time": 162887,
        "text": "蛍光灯夜は点けたままで",
        "cn": "荧光灯依旧点亮着夜"
    },
    {
        "time": 165055,
        "text": "今日はもう遅いから",
        "cn": "今天已经很晚了"
    },
    {
        "time": 166701,
        "text": "今だけはこのままでおやすみ",
        "cn": "现在就先这样吧祝你晚安"
    }
]