[
    {
        "time": 0,
        "text": "",
        "interlude": true
    },
    {
        "time": 26906,
        "text": "言葉の欠片が無いように"
    },
    {
        "time": 29694,
        "text": "なんにも私ら知らないの"
    },
    {
        "time": 32553,
        "text": "教えて教えてどうやって"
    },
    {
        "time": 35033,
        "text": "楽な生き方１ピース"
    },
    {
        "time": 37655,
        "text": "",
        "interlude": true
    },
    {
        "time": 37872,
        "text": "でも余計なことばか知っちゃって"
    },
    {
        "time": 40808,
        "text": "痛いの痛いの今日だって"
    },
    {
        "time": 43280,
        "text": "嗚呼 夜の海底"
    },
    {
        "time": 45987,
        "text": "言えない、言えないよつらいなんて"
    },
    {
        "time": 48724,
        "text": "",
        "interlude": true
    },
    {
        "time": 49077,
        "text": "ねぇココロの隙間"
    },
    {
        "time": 51481,
        "text": "知ってゆく昨日の奥"
    },
    {
        "time": 53529,
        "text": "",
        "interlude": true
    },
    {
        "time": 53979,
        "text": "明日の隣で笑う様に"
    },
    {
        "time": 57140,
        "text": "言葉の底で微睡む様に"
    },
    {
        "time": 59504,
        "text": "なんにも私ら知らないの"
    },
    {
        "time": 62316,
        "text": "嗚呼 ならそれでいいじゃん"
    },
    {
        "time": 65314,
        "text": "つらいのつらいの飛んでかない"
    },
    {
        "time": 67906,
        "text": "なら眠れぬ僕らを抱きしめて"
    },
    {
        "time": 70762,
        "text": "溶けだす季節にループする"
    },
    {
        "time": 73264,
        "text": "嗚呼 ただそれでいいじゃん、なんて。"
    },
    {
        "time": 76756,
        "text": "",
        "interlude": true
    },
    {
        "time": 86863,
        "text": "んー"
    },
    {
        "time": 87030,
        "text": "たーりらったりらっ"
    },
    {
        "time": 88645,
        "text": "たりらイェイイェ"
    },
    {
        "time": 89813,
        "text": "",
        "interlude": true
    },
    {
        "time": 90042,
        "text": "たーりらったりらっ"
    },
    {
        "time": 91194,
        "text": "たりらイェイイェ"
    },
    {
        "time": 92446,
        "text": "",
        "interlude": true
    },
    {
        "time": 92734,
        "text": "たーりらったりらっ"
    },
    {
        "time": 93933,
        "text": "たりらイェイイェ"
    },
    {
        "time": 95309,
        "text": "",
        "interlude": true
    },
    {
        "time": 95509,
        "text": "たーりらったったったった"
    },
    {
        "time": 97375,
        "text": "るるラル"
    },
    {
        "time": 98306,
        "text": "",
        "interlude": true
    },
    {
        "time": 99179,
        "text": "気持ちの欠片"
    },
    {
        "time": 100415,
        "text": "知って征く未来の奥"
    },
    {
        "time": 102618,
        "text": "",
        "interlude": true
    },
    {
        "time": 125309,
        "text": "明日の隣で笑う様に"
    },
    {
        "time": 127840,
        "text": "言葉の底で微睡む様に"
    },
    {
        "time": 130539,
        "text": "なんにも私ら知らないの"
    },
    {
        "time": 133192,
        "text": "嗚呼 ならそれでいいじゃん"
    },
    {
        "time": 135938,
        "text": "つらいのつらいの飛んでかない"
    },
    {
        "time": 138676,
        "text": "なら眠れぬ僕らを抱きしめて"
    },
    {
        "time": 141570,
        "text": "溶けだす季節にループする"
    },
    {
        "time": 144135,
        "text": "嗚呼 ただそれでいいじゃん、なんて。"
    },
    {
        "time": 149921,
        "text": "",
        "interlude": true
    }
]